brainspace/__init__.py
brainspace/_version.py
brainspace/datasets/__init__.py
brainspace/datasets/base.py
brainspace/datasets/matrices/fusion_tutorial/vosdewael_200_mpc_matrix.csv
brainspace/datasets/matrices/holdout_group/schaefer_100_mean_connectivity_matrix.csv
brainspace/datasets/matrices/holdout_group/schaefer_200_mean_connectivity_matrix.csv
brainspace/datasets/matrices/holdout_group/schaefer_300_mean_connectivity_matrix.csv
brainspace/datasets/matrices/holdout_group/schaefer_400_mean_connectivity_matrix.csv
brainspace/datasets/matrices/holdout_group/vosdewael_100_mean_connectivity_matrix.csv
brainspace/datasets/matrices/holdout_group/vosdewael_200_mean_connectivity_matrix.csv
brainspace/datasets/matrices/holdout_group/vosdewael_300_mean_connectivity_matrix.csv
brainspace/datasets/matrices/holdout_group/vosdewael_400_mean_connectivity_matrix.csv
brainspace/datasets/matrices/individual/HCP_111009_maximum_vosdewael_300.csv
brainspace/datasets/matrices/individual/HCP_123824_median_vosdewael_300.csv
brainspace/datasets/matrices/individual/HCP_124624_maximum_schaefer_300.csv
brainspace/datasets/matrices/individual/HCP_124624_minimum_schaefer_200.csv
brainspace/datasets/matrices/individual/HCP_142828_minimum_schaefer_400.csv
brainspace/datasets/matrices/individual/HCP_144125_maximum_schaefer_100.csv
brainspace/datasets/matrices/individual/HCP_149236_maximum_vosdewael_200.csv
brainspace/datasets/matrices/individual/HCP_149236_minimum_vosdewael_100.csv
brainspace/datasets/matrices/individual/HCP_151425_median_vosdewael_400.csv
brainspace/datasets/matrices/individual/HCP_153025_minimum_vosdewael_400.csv
brainspace/datasets/matrices/individual/HCP_169949_median_schaefer_400.csv
brainspace/datasets/matrices/individual/HCP_175540_minimum_schaefer_300.csv
brainspace/datasets/matrices/individual/HCP_188347_maximum_schaefer_200.csv
brainspace/datasets/matrices/individual/HCP_208024_median_vosdewael_100.csv
brainspace-0.1.22.dist-info/licenses/LICENSE
brainspace-0.1.22.dist-info/METADATA
brainspace-0.1.22.dist-info/WHEEL
brainspace-0.1.22.dist-info/top_level.txt
brainspace-0.1.22.dist-info/RECORD
