Metadata-Version: 2.4
Name: brainspace
Version: 0.1.22
Summary: Cortical gradients and beyond
Home-page: https://github.com/MICA-MNI/BrainSpace
Download-URL: https://github.com/MICA-MNI/BrainSpace/archive/0.1.22.tar.gz
Author: BrainSpace developers
Author-email: enning.yang@mcgill.ca
Project-URL: Documentation, https://brainspace.readthedocs.io
Project-URL: Bug Reports, https://github.com/MICA-MNI/BrainSpace/issues
Project-URL: Source, https://github.com/MICA-MNI/BrainSpace
Keywords: brain cortex gradient manifold
Classifier: Development Status :: 3 - Alpha
Classifier: Intended Audience :: Science/Research
Classifier: Intended Audience :: Developers
Classifier: Topic :: Software Development :: Build Tools
Classifier: Topic :: Scientific/Engineering
Classifier: License :: OSI Approved :: BSD License
Classifier: Programming Language :: Python
Classifier: Programming Language :: Python :: 3.5
Classifier: Programming Language :: Python :: 3.6
Classifier: Programming Language :: Python :: 3.7
Classifier: Programming Language :: Python :: 3 :: Only
Requires-Python: >=3.5
License-File: LICENSE
Requires-Dist: numpy>=1.11.0
Requires-Dist: scipy>=0.17.0
Requires-Dist: scikit-learn>=0.20.0
Requires-Dist: matplotlib>=2.0.0
Requires-Dist: vtk>=8.1.0
Requires-Dist: nibabel
Requires-Dist: pillow
Requires-Dist: pandas
Provides-Extra: test
Requires-Dist: pytest; extra == "test"
Requires-Dist: coverage; extra == "test"
Requires-Dist: pytest-cov; extra == "test"
Requires-Dist: coveralls; extra == "test"
Requires-Dist: numpy>=1.11.0; extra == "test"
Requires-Dist: scipy>=0.17.0; extra == "test"
Requires-Dist: scikit-learn>=0.20.0; extra == "test"
Requires-Dist: matplotlib>=2.0.0; extra == "test"
Requires-Dist: vtk>=8.1.0; extra == "test"
Requires-Dist: nibabel; extra == "test"
Requires-Dist: pillow; extra == "test"
Requires-Dist: pandas; extra == "test"
Dynamic: author
Dynamic: author-email
Dynamic: classifier
Dynamic: description
Dynamic: description-content-type
Dynamic: download-url
Dynamic: home-page
Dynamic: keywords
Dynamic: license-file
Dynamic: project-url
Dynamic: provides-extra
Dynamic: requires-dist
Dynamic: requires-python
Dynamic: summary
